[{"Marca": "Alfa Romeo", "A\u00f1o": "1910", "Fundadores": "Nicola Romeo, Alexandre Darracq, Ugo Stella", "Sede": "Tur\u00edn, Italia", "NWallpapers": "445", "Bandera": "Itali-flag"}, {"Marca": "Aston Martin", "A\u00f1o": "1913", "Fundadores": "Lionel Martin, Robert Bamford", "Sede": "Gaydon, Reino Unido", "NWallpapers": "584", "Bandera": "UK-flag"}, {"Marca": "Audi", "A\u00f1o": "1909", "Fundadores": "August Horch", "Sede": "Ingolstadt, ?Alemania", "NWallpapers": "473", "Bandera": "germany-flag"}, {"Marca": "Bentley", "A\u00f1o": "1919", "Fundadores": "Walter Owen Bentley, H. M. Bentley", "Sede": "Crewe, Reino Unido", "NWallpapers": "4", "Bandera": "UK-flag"}, {"Marca": "BMW", "A\u00f1o": "1916", "Fundadores": "Karl Rapp, Gustav Otto, Franz Josef Popp, Camillo Castiglioni", "Sede": "M\u00fanich, Alemania", "NWallpapers": "597", "Bandera": "germany-flag"}, {"Marca": "Bugatti", "A\u00f1o": "1909", "Fundadores": "Ettore Bugatti", "Sede": "Molsheim, Francia", "NWallpapers": "233", "Bandera": "France-flag"}, {"Marca": "Chevrolet", "A\u00f1o": "1911", "Fundadores": " Louis Chevrolet, William Crapo Durant, Arthur Chevrolet, Samuel McLaughlin, Edwin R. Campbell, William Little", "Sede": "Detroit,  USA", "NWallpapers": "294", "Bandera": "USA-flag"}, {"Marca": "Ferrari", "A\u00f1o": "1947", "Fundadores": "Enzo Ferrari", "Sede": "Maranello, Italia", "NWallpapers": "854", "Bandera": "Itali-flag"}, {"Marca": "Ford", "A\u00f1o": "1903", "Fundadores": "Henry Ford", "Sede": "Dearborn, USA", "NWallpapers": "266", "Bandera": "USA-flag"}, {"Marca": "Honda", "A\u00f1o": "1948", "Fundadores": "S?ichir? Honda, Takeo Fujisawa", "Sede": "Minato, Jap\u00f3n", "NWallpapers": "30", "Bandera": "Japon-flag"}, {"Marca": "Jaguar", "A\u00f1o": "1922", "Fundadores": "William Lyons, William Walmsley", "Sede": "Coventry, Reino Unido", "NWallpapers": "88", "Bandera": "UK-flag"}, {"Marca": "Koenigsegg", "A\u00f1o": "1994", "Fundadores": "Christian von Koenigsegg", "Sede": "\u00c4ngelholm, Suecia", "NWallpapers": "359", "Bandera": "Suecia-flag"}, {"Marca": "Lamborghini", "A\u00f1o": "1963", "Fundadores": "Ferruccio Lamborghini", "Sede": "Sant'Agata Bolognese, Italia", "NWallpapers": "570", "Bandera": "Itali-flag"}, {"Marca": "Lotus", "A\u00f1o": "1948", "Fundadores": "Colin Chapman", "Sede": "Norwich, Reino Unido", "NWallpapers": "76", "Bandera": "UK-flag"}, {"Marca": "Maserati", "A\u00f1o": "1914", "Fundadores": "Ernesto Maserati, Ettore Maserati, Alfieri Maserati", "Sede": "M\u00f3dena, Italia", "NWallpapers": "56", "Bandera": "Itali-flag"}, {"Marca": "McLaren", "A\u00f1o": "1989", "Fundadores": "Ron Dennis", "Sede": "Woking, Reino Unido", "NWallpapers": "51", "Bandera": "UK-flag"}, {"Marca": "Mercedes Benz", "A\u00f1o": "1926", "Fundadores": "Carl Benz", "Sede": "Stuttgart, Alemania", "NWallpapers": "332", "Bandera": "germany-flag"}, {"Marca": "Mercedes Maybach", "A\u00f1o": "1909", "Fundadores": "Wilhelm Maybach, Karl Maybach", "Sede": "Stuttgart, Alemania", "NWallpapers": "44", "Bandera": "germany-flag"}, {"Marca": "Mercedes AMG", "A\u00f1o": "1967", "Fundadores": "Hans-Werner Aufrecht, Erhard Melcher", "Sede": "Affalterbach, Alemania", "NWallpapers": "254", "Bandera": "germany-flag"}, {"Marca": "Nissan", "A\u00f1o": "1933", "Fundadores": "Yoshisuke Aikawa, Rokuro Aoyama, Masujiro Hashimoto, William Gorham", "Sede": "Yokohama, Jap\u00f3n", "NWallpapers": "34", "Bandera": "Japon-flag"}, {"Marca": "Pagani", "A\u00f1o": "1992", "Fundadores": "Horacio Pagani", "Sede": "San Cesario sul Panaro, Italia", "NWallpapers": "517", "Bandera": "Itali-flag"}, {"Marca": "Porsche", "A\u00f1o": "1931", "Fundadores": "Ferdinand Porsche", "Sede": "Stuttgart, Alemania", "NWallpapers": "762", "Bandera": "germany-flag"}, {"Marca": "Rolls-Royce", "A\u00f1o": "1904", "Fundadores": "Henry Royce, Charles Rolls", "Sede": "Westhampnett, Reino Unido", "NWallpapers": "5", "Bandera": "UK-flag"}]